gene_synthesis/__init__.py
gene_synthesis/lib.py
gene_synthesis-0.1.data/scripts/gene_synthesis
gene_synthesis-0.1.dist-info/LICENSE
gene_synthesis-0.1.dist-info/METADATA
gene_synthesis-0.1.dist-info/WHEEL
gene_synthesis-0.1.dist-info/top_level.txt
gene_synthesis-0.1.dist-info/RECORD
