Metadata-Version: 2.1
Name: gene_synthesis
Version: 0.1
Summary: gene synthesis design
Home-page: https://github.com/shiqiang-lin/gene-synthesis
Author: Shiqiang Lin
Author-email: linshiqiang@fafu.edu.cn
License: MIT
Keywords: gene synthesis,gene cloning,PCR
Classifier: Development Status :: 5 - Production/Stable
Classifier: License :: OSI Approved :: MIT License
Classifier: Programming Language :: Python :: 3.10
Classifier: Topic :: Scientific/Engineering
Classifier: Operating System :: MacOS
Classifier: Operating System :: Microsoft :: Windows
License-File: LICENSE
Requires-Dist: biopython
Requires-Dist: matplotlib
